vaklm/__init__.py
vaklm/vaklm.py
vaklm-0.3.1.dist-info/METADATA
vaklm-0.3.1.dist-info/WHEEL
vaklm-0.3.1.dist-info/top_level.txt
vaklm-0.3.1.dist-info/RECORD
